MANIFEST.in
README.md
requirements.txt
setup.cfg
setup.py
inferout/__init__.py
inferout/cluster.py
inferout/constants.py
inferout/exceptions.py
inferout/management_api.py
inferout/models.py
inferout/scheduler.py
inferout/serving_api.py
inferout/utils.py
inferout/worker.py
inferout/worker_annotators.py
inferout.egg-info/PKG-INFO
inferout.egg-info/SOURCES.txt
inferout.egg-info/dependency_links.txt
inferout.egg-info/entry_points.txt
inferout.egg-info/requires.txt
inferout.egg-info/top_level.txt
inferout/plugins/__init__.py
inferout/plugins/base.py
inferout/plugins/k8s.py
inferout/serving_engines/__init__.py
inferout/serving_engines/base.py
inferout/serving_engines/echo.py
inferout/storage_engines/__init__.py
inferout/storage_engines/aws_s3.py
inferout/storage_engines/base.py
inferout/storage_engines/local_files.py